quantum_ciphers/Quantum_Ciphers.py
quantum_ciphers/__init__.py
Quantum_Ciphers-3.0.3.dist-info/LICENSE.txt
Quantum_Ciphers-3.0.3.dist-info/METADATA
Quantum_Ciphers-3.0.3.dist-info/WHEEL
Quantum_Ciphers-3.0.3.dist-info/top_level.txt
Quantum_Ciphers-3.0.3.dist-info/RECORD
