Metadata-Version: 2.1
Name: Quantum-Ciphers
Version: 3.0.3
Summary: A package of diffenent easy-to-use text ciphers.
Home-page: https://github.com/GrandMoff100/Quantum_Cipher2
Author: Quantum_Wizard
Author-email: minecraftcrusher100@gmail.com
License: UNKNOWN
Platform: UNKNOWN
Classifier: Programming Language :: Python :: 3
Classifier: License :: OSI Approved :: MIT License
Requires-Python: >=3.7
Requires-Dist: omegamath01
